auditdpythonparser/__init__.py
auditdpythonparser/auditdparser.py
auditd_python_parser-0.0.9.dist-info/LICENSE
auditd_python_parser-0.0.9.dist-info/METADATA
auditd_python_parser-0.0.9.dist-info/WHEEL
auditd_python_parser-0.0.9.dist-info/top_level.txt
auditd_python_parser-0.0.9.dist-info/RECORD
