Metadata-Version: 2.1
Name: auditd-python-parser
Version: 0.0.9
Summary: A python package to parse & process raw auditd.log files
Home-page: https://github.com/exeronn/auditd-python-parser
Author: exeron
Project-URL: Bug Tracker, https://github.com/exeronn/auditd-python-parser/issues
Project-URL: repository, https://github.com/exeronn/auditd-python-parser
Classifier: Programming Language :: Python :: 3
Classifier: License :: OSI Approved :: GNU General Public License v3 (GPLv3)
Classifier: Operating System :: OS Independent
Requires-Python: >=3
License-File: LICENSE
Requires-Dist: pandas (>=1.3.5)
